knps/__init__.py
knps/knps_cli.py
knps/settings.py
knps_cli-0.1.9.2.dist-info/LICENSE
knps_cli-0.1.9.2.dist-info/METADATA
knps_cli-0.1.9.2.dist-info/WHEEL
knps_cli-0.1.9.2.dist-info/entry_points.txt
knps_cli-0.1.9.2.dist-info/top_level.txt
knps_cli-0.1.9.2.dist-info/RECORD
