Metadata-Version: 2.1
Name: knps-cli
Version: 0.1.9.2
Summary: KNPS Command Line Interface
Home-page: https://github.com/KNPSystem/cli
Author: Mike Anderson
Author-email: mrander@gmail.com
License: UNKNOWN
Project-URL: Bug Tracker, https://github.com/KNPSystem/cli/issues
Platform: UNKNOWN
Classifier: Programming Language :: Python :: 3
Classifier: License :: OSI Approved :: MIT License
Classifier: Operating System :: MacOS :: MacOS X
Requires-Python: >=3.8
License-File: LICENSE
Requires-Dist: requests (==2.27.1)
Requires-Dist: PyPDF2 (==1.26.0)
Requires-Dist: pyyaml (==6.0)
Requires-Dist: binaryornot (==0.4.4)
Requires-Dist: psutil (==5.9.0)
Requires-Dist: watchdog (==2.1.6)
